Metadata-Version: 2.1
Name: greenplum-python
Version: 1.1.0
Summary: Python interface for Greenplum and Postgres
Author-email: greenplum-python@vmware.com
Maintainer-email: greenplum-python@vmware.com
License: Apache Software License
Classifier: License :: OSI Approved :: Apache Software License
Classifier: Operating System :: OS Independent
Classifier: Programming Language :: Python :: 3
Requires-Python: >=3.9
License-File: LICENSE
Requires-Dist: psycopg2-binary ==2.9.5
Requires-Dist: dill ==0.3.6
